container_env/__init__.py
container_env-0.1.0.dist-info/LICENSE
container_env-0.1.0.dist-info/WHEEL
container_env-0.1.0.dist-info/METADATA
container_env-0.1.0.dist-info/RECORD
