Metadata-Version: 2.1
Name: container-env
Version: 0.1.0
Summary: 
Home-page: https://lkummer.github.io/container-env/
License: MIT
Keywords: Container,Docker,Environment,Configuration,Secrets
Author: Lior Kummer
Requires-Python: >=3.8,<4.0
Classifier: Development Status :: 3 - Alpha
Classifier: Environment :: Console
Classifier: Framework :: Django
Classifier: Framework :: Flask
Classifier: Intended Audience :: Developers
Classifier: License :: OSI Approved :: MIT License
Classifier: Programming Language :: Python :: 3
Classifier: Programming Language :: Python :: 3.8
Classifier: Topic :: Software Development
Project-URL: Documentation, https://lkummer.github.io/container-env/guide/
Project-URL: Repository, https://github.com/LKummer/container-env
